<annotation>
	<folder>JPEGImages</folder>
	<filename>Dangerous1157.jpg</filename>
	<path>E:\1.code\1.data_harness\VOC-harness_person\JPEGImages\Dangerous1157.jpg</path>
	<source>
		<database>Unknown</database>
	</source>
	<size>
		<width>640</width>
		<height>439</height>
		<depth>3</depth>
	</size>
	<segmented>0</segmented>
	<object>
		<name>clothes</name>
		<pose>Unspecified</pose>
		<truncated>0</truncated>
		<difficult>0</difficult>
		<bndbox>
			<xmin>231</xmin>
			<ymin>61</ymin>
			<xmax>361</xmax>
			<ymax>166</ymax>
		</bndbox>
	</object>
	<object>
		<name>person</name>
		<pose>Unspecified</pose>
		<truncated>0</truncated>
		<difficult>0</difficult>
		<bndbox>
			<xmin>119</xmin>
			<ymin>11</ymin>
			<xmax>456</xmax>
			<ymax>406</ymax>
		</bndbox>
	</object>
</annotation>