<annotation>
	<folder>data_add_person</folder>
	<filename>Dangerous1971.jpg</filename>
	<path>E:\1.code\1.data_harness\data_add_person\Dangerous1971.jpg</path>
	<source>
		<database>Unknown</database>
	</source>
	<size>
		<width>1920</width>
		<height>1080</height>
		<depth>3</depth>
	</size>
	<segmented>0</segmented>
	<object>
		<name>clothes</name>
		<pose>Unspecified</pose>
		<truncated>0</truncated>
		<difficult>0</difficult>
		<bndbox>
			<xmin>541</xmin>
			<ymin>524</ymin>
			<xmax>822</xmax>
			<ymax>835</ymax>
		</bndbox>
	</object>
	<object>
		<name>person</name>
		<pose>Unspecified</pose>
		<truncated>0</truncated>
		<difficult>0</difficult>
		<bndbox>
			<xmin>506</xmin>
			<ymin>438</ymin>
			<xmax>819</xmax>
			<ymax>974</ymax>
		</bndbox>
	</object>
</annotation>