<annotation>
	<folder>JPEGImages</folder>
	<filename>Dangerous1597.jpg</filename>
	<path>E:\1.code\1.data_harness\VOC-harness_person\JPEGImages\Dangerous1597.jpg</path>
	<source>
		<database>Unknown</database>
	</source>
	<size>
		<width>500</width>
		<height>368</height>
		<depth>3</depth>
	</size>
	<segmented>0</segmented>
	<object>
		<name>clothes</name>
		<pose>Unspecified</pose>
		<truncated>0</truncated>
		<difficult>0</difficult>
		<bndbox>
			<xmin>182</xmin>
			<ymin>172</ymin>
			<xmax>216</xmax>
			<ymax>214</ymax>
		</bndbox>
	</object>
	<object>
		<name>clothes</name>
		<pose>Unspecified</pose>
		<truncated>0</truncated>
		<difficult>0</difficult>
		<bndbox>
			<xmin>245</xmin>
			<ymin>185</ymin>
			<xmax>290</xmax>
			<ymax>242</ymax>
		</bndbox>
	</object>
	<object>
		<name>clothes</name>
		<pose>Unspecified</pose>
		<truncated>0</truncated>
		<difficult>0</difficult>
		<bndbox>
			<xmin>152</xmin>
			<ymin>229</ymin>
			<xmax>197</xmax>
			<ymax>268</ymax>
		</bndbox>
	</object>
	<object>
		<name>clothes</name>
		<pose>Unspecified</pose>
		<truncated>0</truncated>
		<difficult>0</difficult>
		<bndbox>
			<xmin>309</xmin>
			<ymin>242</ymin>
			<xmax>363</xmax>
			<ymax>311</ymax>
		</bndbox>
	</object>
	<object>
		<name>clothes</name>
		<pose>Unspecified</pose>
		<truncated>0</truncated>
		<difficult>0</difficult>
		<bndbox>
			<xmin>380</xmin>
			<ymin>264</ymin>
			<xmax>456</xmax>
			<ymax>366</ymax>
		</bndbox>
	</object>
	<object>
		<name>clothes</name>
		<pose>Unspecified</pose>
		<truncated>0</truncated>
		<difficult>0</difficult>
		<bndbox>
			<xmin>389</xmin>
			<ymin>21</ymin>
			<xmax>425</xmax>
			<ymax>67</ymax>
		</bndbox>
	</object>
	<object>
		<name>clothes</name>
		<pose>Unspecified</pose>
		<truncated>0</truncated>
		<difficult>0</difficult>
		<bndbox>
			<xmin>445</xmin>
			<ymin>28</ymin>
			<xmax>482</xmax>
			<ymax>82</ymax>
		</bndbox>
	</object>
	<object>
		<name>person</name>
		<pose>Unspecified</pose>
		<truncated>0</truncated>
		<difficult>0</difficult>
		<bndbox>
			<xmin>288</xmin>
			<ymin>218</ymin>
			<xmax>368</xmax>
			<ymax>367</ymax>
		</bndbox>
	</object>
	<object>
		<name>person</name>
		<pose>Unspecified</pose>
		<truncated>0</truncated>
		<difficult>0</difficult>
		<bndbox>
			<xmin>232</xmin>
			<ymin>159</ymin>
			<xmax>291</xmax>
			<ymax>342</ymax>
		</bndbox>
	</object>
	<object>
		<name>person</name>
		<pose>Unspecified</pose>
		<truncated>0</truncated>
		<difficult>0</difficult>
		<bndbox>
			<xmin>174</xmin>
			<ymin>148</ymin>
			<xmax>227</xmax>
			<ymax>310</ymax>
		</bndbox>
	</object>
	<object>
		<name>person</name>
		<pose>Unspecified</pose>
		<truncated>1</truncated>
		<difficult>0</difficult>
		<bndbox>
			<xmin>378</xmin>
			<ymin>1</ymin>
			<xmax>435</xmax>
			<ymax>157</ymax>
		</bndbox>
	</object>
	<object>
		<name>person</name>
		<pose>Unspecified</pose>
		<truncated>0</truncated>
		<difficult>0</difficult>
		<bndbox>
			<xmin>428</xmin>
			<ymin>7</ymin>
			<xmax>499</xmax>
			<ymax>169</ymax>
		</bndbox>
	</object>
	<object>
		<name>person</name>
		<pose>Unspecified</pose>
		<truncated>0</truncated>
		<difficult>0</difficult>
		<bndbox>
			<xmin>340</xmin>
			<ymin>208</ymin>
			<xmax>466</xmax>
			<ymax>367</ymax>
		</bndbox>
	</object>
	<object>
		<name>person</name>
		<pose>Unspecified</pose>
		<truncated>0</truncated>
		<difficult>0</difficult>
		<bndbox>
			<xmin>146</xmin>
			<ymin>228</ymin>
			<xmax>213</xmax>
			<ymax>360</ymax>
		</bndbox>
	</object>
</annotation>