<annotation>
	<folder>JPEGImages</folder>
	<filename>SafetyHarness0765.jpg</filename>
	<path>E:\1.code\1.data_harness\VOC-harness_person\JPEGImages\SafetyHarness0765.jpg</path>
	<source>
		<database>Unknown</database>
	</source>
	<size>
		<width>495</width>
		<height>481</height>
		<depth>3</depth>
	</size>
	<segmented>0</segmented>
	<object>
		<name>safety-harness</name>
		<pose>Unspecified</pose>
		<truncated>0</truncated>
		<difficult>0</difficult>
		<bndbox>
			<xmin>265</xmin>
			<ymin>74</ymin>
			<xmax>421</xmax>
			<ymax>249</ymax>
		</bndbox>
	</object>
	<object>
		<name>person</name>
		<pose>Unspecified</pose>
		<truncated>0</truncated>
		<difficult>0</difficult>
		<bndbox>
			<xmin>212</xmin>
			<ymin>2</ymin>
			<xmax>492</xmax>
			<ymax>470</ymax>
		</bndbox>
	</object>
</annotation>